pimux/Sensors.py
pimux/__init__.py
pimux/function.py
pimux/scrip.py
pimux-2.0.2.dist-info/LICENSE
pimux-2.0.2.dist-info/METADATA
pimux-2.0.2.dist-info/WHEEL
pimux-2.0.2.dist-info/top_level.txt
pimux-2.0.2.dist-info/RECORD
