Metadata-Version: 2.1
Name: pimux
Version: 2.0.2
Summary: A package for accessing termux-api
Home-page: https://github.com/azwyane/pymux.git
Author: azwane
Author-email: debianbyte@gmail.com
License: UNKNOWN
Platform: UNKNOWN
Classifier: Programming Language :: Python :: 3
Classifier: License :: OSI Approved :: MIT License
Classifier: Operating System :: OS Independent
Requires-Python: >=3.6
